webagents/__init__.py
webagents/__main__.py
webagents/agents/__init__.py
webagents/agents/core/__init__.py
webagents/agents/core/base_agent.py
webagents/agents/core/handoffs.py
webagents/agents/handoffs/__init__.py
webagents/agents/interfaces/__init__.py
webagents/agents/lifecycle/__init__.py
webagents/agents/skills/__init__.py
webagents/agents/skills/base.py
webagents/agents/skills/core/__init__.py
webagents/agents/skills/core/guardrails/__init__.py
webagents/agents/skills/core/llm/__init__.py
webagents/agents/skills/core/llm/anthropic/__init__.py
webagents/agents/skills/core/llm/litellm/__init__.py
webagents/agents/skills/core/llm/litellm/skill.py
webagents/agents/skills/core/llm/openai/__init__.py
webagents/agents/skills/core/llm/xai/__init__.py
webagents/agents/skills/core/mcp/README.md
webagents/agents/skills/core/mcp/__init__.py
webagents/agents/skills/core/mcp/skill.py
webagents/agents/skills/core/memory/__init__.py
webagents/agents/skills/core/memory/long_term_memory/__init__.py
webagents/agents/skills/core/memory/long_term_memory/memory_skill.py
webagents/agents/skills/core/memory/short_term_memory/__init__.py
webagents/agents/skills/core/memory/short_term_memory/skill.py
webagents/agents/skills/core/memory/vector_memory/skill.py
webagents/agents/skills/core/planning/__init__.py
webagents/agents/skills/core/planning/planner.py
webagents/agents/skills/ecosystem/__init__.py
webagents/agents/skills/ecosystem/crewai/__init__.py
webagents/agents/skills/ecosystem/crewai/skill.py
webagents/agents/skills/ecosystem/database/__init__.py
webagents/agents/skills/ecosystem/database/skill.py
webagents/agents/skills/ecosystem/filesystem/__init__.py
webagents/agents/skills/ecosystem/google/__init__.py
webagents/agents/skills/ecosystem/google/calendar/__init__.py
webagents/agents/skills/ecosystem/google/calendar/skill.py
webagents/agents/skills/ecosystem/mongodb/__init__.py
webagents/agents/skills/ecosystem/mongodb/skill.py
webagents/agents/skills/ecosystem/n8n/README.md
webagents-0.2.3.dist-info/METADATA
webagents-0.2.3.dist-info/WHEEL
webagents-0.2.3.dist-info/entry_points.txt
webagents-0.2.3.dist-info/licenses/LICENSE
webagents-0.2.3.dist-info/RECORD
